storage/__init__.py
storage/accessor.py
storage/auditor.py
storage/bootstrap.py
storage/database.py
storage/hooks.py
storage/io_helpers.py
storage/router_database.py
storage/router_model.py
storage/utils.py
vention_storage-0.5.4.dist-info/METADATA
vention_storage-0.5.4.dist-info/WHEEL
vention_storage-0.5.4.dist-info/RECORD
