Metadata-Version: 2.1
Name: vention-storage
Version: 0.5.4
Summary: A framework for storing and managing component and application data for machine apps.
License: Proprietary
Author: VentionCo
Requires-Python: >=3.10,<3.11
Classifier: License :: Other/Proprietary License
Classifier: Programming Language :: Python :: 3
Classifier: Programming Language :: Python :: 3.10
Requires-Dist: fastapi (==0.121.1)
Requires-Dist: python-multipart (>=0.0.20,<0.0.21)
Requires-Dist: sqlmodel (==0.0.27)
Requires-Dist: uvicorn (>=0.35.0,<0.36.0)
